mcp_applemusic.py
mcp_applemusic-0.1.5.dist-info/METADATA
mcp_applemusic-0.1.5.dist-info/WHEEL
mcp_applemusic-0.1.5.dist-info/entry_points.txt
mcp_applemusic-0.1.5.dist-info/top_level.txt
mcp_applemusic-0.1.5.dist-info/RECORD
