Metadata-Version: 2.4
Name: mcp-applemusic
Version: 0.1.5
Summary: A simple Apple Music API client for MCP
Requires-Python: >=3.13
Requires-Dist: mcp>=1.2.1
